{
  "{\"_child\": {\"100\": {\"code\": 2, \"name\": \"安踏\"}, \"10004\": {\"code\": 4, \"name\": \"安踏儿童\"}, \"10009\": {\"code\": 9, \"name\": \"电商\"}}, \"code\": \"k\", \"code_order\": 25, \"codename\": \"品牌\"}": {
    "element": {
      "_child": {
        "100": {
          "code": 2,
          "name": "安踏"
        },
        "10004": {
          "code": 4,
          "name": "安踏儿童"
        },
        "10009": {
          "code": 9,
          "name": "电商"
        }
      },
      "code": "k",
      "code_order": 25,
      "codename": "品牌"
    },
    "missing_in": [
      "child_shoes_new_bar",
      "man_cotton_shoes_new_bar"
    ]
  },
  "{\"_child\": {\"25\": {\"code\": 72, \"name\": \"22\"}, \"26\": {\"code\": 73, \"name\": \"23\"}, \"27\": {\"code\": 74, \"name\": \"24\"}, \"28\": {\"code\": 75, \"name\": \"25\"}, \"29\": {\"code\": 43, \"name\": \"26\"}, \"30\": {\"code\": 44, \"name\": \"27\"}, \"31\": {\"code\": 40, \"name\": \"28\"}, \"32\": {\"code\": 41, \"name\": \"29\"}, \"33\": {\"code\": 42, \"name\": \"30\"}, \"34\": {\"code\": 22, \"name\": \"31\"}, \"35\": {\"code\": 23, \"name\": \"32\"}, \"36\": {\"code\": 20, \"name\": \"33\"}, \"37\": {\"code\": 21, \"name\": \"34\"}, \"38\": {\"code\": 13, \"name\": \"35\"}, \"40\": {\"code\": 14, \"name\": \"36\"}, \"42\": {\"code\": 15, \"name\": \"37\"}, \"44\": {\"code\": 16, \"name\": \"38\"}, \"46\": {\"code\": 7, \"name\": \"39\"}, \"47\": {\"code\": 8, \"name\": \"40\"}, \"49\": {\"code\": 9, \"name\": \"41\"}, \"51\": {\"code\": 10, \"name\": \"42\"}}, \"code\": \"c\", \"code_order\": 27, \"codename\": \"尺码\"}": {
    "element": {
      "_child": {
        "25": {
          "code": 72,
          "name": "22"
        },
        "26": {
          "code": 73,
          "name": "23"
        },
        "27": {
          "code": 74,
          "name": "24"
        },
        "28": {
          "code": 75,
          "name": "25"
        },
        "29": {
          "code": 43,
          "name": "26"
        },
        "30": {
          "code": 44,
          "name": "27"
        },
        "31": {
          "code": 40,
          "name": "28"
        },
        "32": {
          "code": 41,
          "name": "29"
        },
        "33": {
          "code": 42,
          "name": "30"
        },
        "34": {
          "code": 22,
          "name": "31"
        },
        "35": {
          "code": 23,
          "name": "32"
        },
        "36": {
          "code": 20,
          "name": "33"
        },
        "37": {
          "code": 21,
          "name": "34"
        },
        "38": {
          "code": 13,
          "name": "35"
        },
        "40": {
          "code": 14,
          "name": "36"
        },
        "42": {
          "code": 15,
          "name": "37"
        },
        "44": {
          "code": 16,
          "name": "38"
        },
        "46": {
          "code": 7,
          "name": "39"
        },
        "47": {
          "code": 8,
          "name": "40"
        },
        "49": {
          "code": 9,
          "name": "41"
        },
        "51": {
          "code": 10,
          "name": "42"
        }
      },
      "code": "c",
      "code_order": 27,
      "codename": "尺码"
    },
    "missing_in": [
      "all_new_bar",
      "man_new_bar",
      "man_shoes_new_bar",
      "man_cotton_shoes_new_bar"
    ]
  },
  "{\"_child\": {\"3\": {\"code\": 7, \"name\": \"户外系列\"}, \"4\": {\"code\": 3, \"name\": \"足球系列\"}, \"5\": {\"code\": 8, \"name\": \"综训系列\"}, \"6\": {\"code\": 9, \"name\": \"生活系列\"}, \"7\": {\"code\": 2, \"name\": \"篮球系列\"}, \"8\": {\"code\": 6, \"name\": \"跑步系列\"}}, \"code\": \"g\", \"code_order\": 23, \"codename\": \"系列\"}": {
    "element": {
      "_child": {
        "3": {
          "code": 7,
          "name": "户外系列"
        },
        "4": {
          "code": 3,
          "name": "足球系列"
        },
        "5": {
          "code": 8,
          "name": "综训系列"
        },
        "6": {
          "code": 9,
          "name": "生活系列"
        },
        "7": {
          "code": 2,
          "name": "篮球系列"
        },
        "8": {
          "code": 6,
          "name": "跑步系列"
        }
      },
      "code": "g",
      "code_order": 23,
      "codename": "系列"
    },
    "missing_in": [
      "all_new_bar",
      "man_cotton_shoes_new_bar"
    ]
  },
  "{\"_child\": {\"1\": {\"code\": 3, \"name\": \"春季\"}, \"2\": {\"code\": 2, \"name\": \"夏季\"}, \"3\": {\"code\": 4, \"name\": \"秋季\"}, \"4\": {\"code\": 1, \"name\": \"冬季\"}}, \"code\": \"m\", \"code_order\": 26, \"codename\": \"季节\"}": {
    "element": {
      "_child": {
        "1": {
          "code": 3,
          "name": "春季"
        },
        "2": {
          "code": 2,
          "name": "夏季"
        },
        "3": {
          "code": 4,
          "name": "秋季"
        },
        "4": {
          "code": 1,
          "name": "冬季"
        }
      },
      "code": "m",
      "code_order": 26,
      "codename": "季节"
    },
    "missing_in": [
      "man_cotton_shoes_new_bar"
    ]
  },
  "{\"_child\": {\"10\": {\"code\": 14, \"name\": \"防泼水\"}, \"14\": {\"code\": 9, \"name\": \"抗菌\"}}, \"code\": \"h\", \"code_order\": 21, \"codename\": \"科技\"}": {
    "element": {
      "_child": {
        "10": {
          "code": 14,
          "name": "防泼水"
        },
        "14": {
          "code": 9,
          "name": "抗菌"
        }
      },
      "code": "h",
      "code_order": 21,
      "codename": "科技"
    },
    "missing_in": [
      "child_shoes_new_bar",
      "man_new_bar",
      "man_shoes_new_bar",
      "man_cotton_shoes_new_bar"
    ]
  },
  "{\"_child\": {\"3\": {\"code\": 7, \"name\": \"户外系列\"}, \"6\": {\"code\": 9, \"name\": \"生活系列\"}}, \"code\": \"g\", \"code_order\": 23, \"codename\": \"系列\"}": {
    "element": {
      "_child": {
        "3": {
          "code": 7,
          "name": "户外系列"
        },
        "6": {
          "code": 9,
          "name": "生活系列"
        }
      },
      "code": "g",
      "code_order": 23,
      "codename": "系列"
    },
    "missing_in": [
      "child_shoes_new_bar",
      "all_new_bar",
      "man_new_bar",
      "man_shoes_new_bar"
    ]
  },
  "{\"_child\": {\"13\": {\"code\": 13, \"name\": \"大童\"}, \"8\": {\"code\": 8, \"name\": \"小童\"}}, \"code\": \"y\", \"code_order\": 8, \"codename\": \"年龄段\"}": {
    "element": {
      "_child": {
        "13": {
          "code": 13,
          "name": "大童"
        },
        "8": {
          "code": 8,
          "name": "小童"
        }
      },
      "code": "y",
      "code_order": 8,
      "codename": "年龄段"
    },
    "missing_in": [
      "child_shoes_new_bar",
      "all_new_bar",
      "man_new_bar",
      "man_shoes_new_bar"
    ]
  },
  "{\"_child\": {\"11\": {\"code\": 13, \"name\": \"棉服\"}, \"12\": {\"code\": 8, \"name\": \"羽绒服\"}, \"125\": {\"code\": 125, \"name\": \"中裤\"}, \"167\": {\"code\": 167, \"name\": \"马甲\"}, \"206\": {\"code\": 206, \"name\": \"凉拖鞋\"}, \"21\": {\"code\": 18, \"name\": \"编织衫\"}, \"34\": {\"code\": 6, \"name\": \"户外鞋\"}, \"347\": {\"code\": 347, \"name\": \"梭织厚外套\"}, \"39\": {\"code\": 5, \"name\": \"综训鞋\"}, \"40\": {\"code\": 4, \"name\": \"板鞋\"}, \"41\": {\"code\": 3, \"name\": \"休闲鞋\"}, \"42\": {\"code\": 1, \"name\": \"篮球鞋\"}, \"43\": {\"code\": 43, \"name\": \"短T\"}, \"45\": {\"code\": 45, \"name\": \"梭织薄外套\"}, \"47\": {\"code\": 47, \"name\": \"帽类\"}, \"48\": {\"code\": 48, \"name\": \"长T\"}, \"52\": {\"code\": 52, \"name\": \"袜类\"}, \"53\": {\"code\": 53, \"name\": \"短裤\"}, \"55\": {\"code\": 55, \"name\": \"两件套\"}, \"56\": {\"code\": 56, \"name\": \"套装\"}, \"59\": {\"code\": 59, \"name\": \"沙滩鞋\"}, \"6\": {\"code\": 29, \"name\": \"包类\"}, \"60\": {\"code\": 60, \"name\": \"背心\"}, \"62\": {\"code\": 62, \"name\": \"长裤\"}, \"63\": {\"code\": 63, \"name\": \"球类\"}, \"663\": {\"code\": 663, \"name\": \"裤装两件套\"}, \"67\": {\"code\": 67, \"name\": \"套头衫\"}, \"86\": {\"code\": 86, \"name\": \"针织运动上衣\"}, \"9\": {\"code\": 37, \"name\": \"七分裤\"}}, \"code\": \"f\", \"code_order\": 28, \"codename\": \"品类\"}": {
    "element": {
      "_child": {
        "11": {
          "code": 13,
          "name": "棉服"
        },
        "12": {
          "code": 8,
          "name": "羽绒服"
        },
        "125": {
          "code": 125,
          "name": "中裤"
        },
        "167": {
          "code": 167,
          "name": "马甲"
        },
        "206": {
          "code": 206,
          "name": "凉拖鞋"
        },
        "21": {
          "code": 18,
          "name": "编织衫"
        },
        "34": {
          "code": 6,
          "name": "户外鞋"
        },
        "347": {
          "code": 347,
          "name": "梭织厚外套"
        },
        "39": {
          "code": 5,
          "name": "综训鞋"
        },
        "40": {
          "code": 4,
          "name": "板鞋"
        },
        "41": {
          "code": 3,
          "name": "休闲鞋"
        },
        "42": {
          "code": 1,
          "name": "篮球鞋"
        },
        "43": {
          "code": 43,
          "name": "短T"
        },
        "45": {
          "code": 45,
          "name": "梭织薄外套"
        },
        "47": {
          "code": 47,
          "name": "帽类"
        },
        "48": {
          "code": 48,
          "name": "长T"
        },
        "52": {
          "code": 52,
          "name": "袜类"
        },
        "53": {
          "code": 53,
          "name": "短裤"
        },
        "55": {
          "code": 55,
          "name": "两件套"
        },
        "56": {
          "code": 56,
          "name": "套装"
        },
        "59": {
          "code": 59,
          "name": "沙滩鞋"
        },
        "6": {
          "code": 29,
          "name": "包类"
        },
        "60": {
          "code": 60,
          "name": "背心"
        },
        "62": {
          "code": 62,
          "name": "长裤"
        },
        "63": {
          "code": 63,
          "name": "球类"
        },
        "663": {
          "code": 663,
          "name": "裤装两件套"
        },
        "67": {
          "code": 67,
          "name": "套头衫"
        },
        "86": {
          "code": 86,
          "name": "针织运动上衣"
        },
        "9": {
          "code": 37,
          "name": "七分裤"
        }
      },
      "code": "f",
      "code_order": 28,
      "codename": "品类"
    },
    "missing_in": [
      "child_shoes_new_bar",
      "all_new_bar",
      "man_shoes_new_bar",
      "man_cotton_shoes_new_bar"
    ]
  },
  "{\"_child\": {\"206\": {\"code\": 206, \"name\": \"凉拖鞋\"}, \"34\": {\"code\": 6, \"name\": \"户外鞋\"}, \"39\": {\"code\": 5, \"name\": \"综训鞋\"}, \"40\": {\"code\": 4, \"name\": \"板鞋\"}, \"41\": {\"code\": 3, \"name\": \"休闲鞋\"}, \"42\": {\"code\": 1, \"name\": \"篮球鞋\"}, \"43\": {\"code\": 2, \"name\": \"跑鞋\"}, \"59\": {\"code\": 59, \"name\": \"沙滩鞋\"}, \"9\": {\"code\": 26, \"name\": \"棉鞋\"}}, \"code\": \"f\", \"code_order\": 28, \"codename\": \"品类\"}": {
    "element": {
      "_child": {
        "206": {
          "code": 206,
          "name": "凉拖鞋"
        },
        "34": {
          "code": 6,
          "name": "户外鞋"
        },
        "39": {
          "code": 5,
          "name": "综训鞋"
        },
        "40": {
          "code": 4,
          "name": "板鞋"
        },
        "41": {
          "code": 3,
          "name": "休闲鞋"
        },
        "42": {
          "code": 1,
          "name": "篮球鞋"
        },
        "43": {
          "code": 2,
          "name": "跑鞋"
        },
        "59": {
          "code": 59,
          "name": "沙滩鞋"
        },
        "9": {
          "code": 26,
          "name": "棉鞋"
        }
      },
      "code": "f",
      "code_order": 28,
      "codename": "品类"
    },
    "missing_in": [
      "child_shoes_new_bar",
      "all_new_bar",
      "man_new_bar",
      "man_cotton_shoes_new_bar"
    ]
  },
  "{\"_child\": {\"100\": {\"code\": 2, \"name\": \"安踏\"}, \"10004\": {\"code\": 4, \"name\": \"安踏儿童\"}}, \"code\": \"k\", \"code_order\": 25, \"codename\": \"品牌\"}": {
    "element": {
      "_child": {
        "100": {
          "code": 2,
          "name": "安踏"
        },
        "10004": {
          "code": 4,
          "name": "安踏儿童"
        }
      },
      "code": "k",
      "code_order": 25,
      "codename": "品牌"
    },
    "missing_in": [
      "child_shoes_new_bar",
      "all_new_bar",
      "man_new_bar",
      "man_shoes_new_bar"
    ]
  },
  "{\"_child\": {\"1\": {\"code\": 3, \"name\": \"春季\"}, \"4\": {\"code\": 1, \"name\": \"冬季\"}}, \"code\": \"m\", \"code_order\": 26, \"codename\": \"季节\"}": {
    "element": {
      "_child": {
        "1": {
          "code": 3,
          "name": "春季"
        },
        "4": {
          "code": 1,
          "name": "冬季"
        }
      },
      "code": "m",
      "code_order": 26,
      "codename": "季节"
    },
    "missing_in": [
      "child_shoes_new_bar",
      "all_new_bar",
      "man_new_bar",
      "man_shoes_new_bar"
    ]
  },
  "{\"_child\": {\"1\": {\"code\": 1, \"name\": \"男\"}, \"2\": {\"code\": 2, \"name\": \"女\"}, \"4\": {\"code\": 3, \"name\": \"中性\"}}, \"code\": \"j\", \"code_order\": 30, \"codename\": \"性别\"}": {
    "element": {
      "_child": {
        "1": {
          "code": 1,
          "name": "男"
        },
        "2": {
          "code": 2,
          "name": "女"
        },
        "4": {
          "code": 3,
          "name": "中性"
        }
      },
      "code": "j",
      "code_order": 30,
      "codename": "性别"
    },
    "missing_in": [
      "man_new_bar",
      "man_shoes_new_bar",
      "man_cotton_shoes_new_bar"
    ]
  },
  "{\"_child\": {\"1\": {\"code\": 1, \"name\": \"黑色\"}, \"10\": {\"code\": 10, \"name\": \"灰色\"}, \"11\": {\"code\": 11, \"name\": \"粉色\"}, \"12\": {\"code\": 12, \"name\": \"棕色\"}, \"2\": {\"code\": 2, \"name\": \"白色\"}, \"3\": {\"code\": 3, \"name\": \"红色\"}, \"4\": {\"code\": 4, \"name\": \"橙色\"}, \"5\": {\"code\": 5, \"name\": \"黄色\"}, \"6\": {\"code\": 6, \"name\": \"绿色\"}, \"7\": {\"code\": 7, \"name\": \"青色\"}, \"8\": {\"code\": 8, \"name\": \"蓝色\"}, \"9\": {\"code\": 9, \"name\": \"紫色\"}}, \"code\": \"b\", \"code_order\": 4, \"codename\": \"颜色\"}": {
    "element": {
      "_child": {
        "1": {
          "code": 1,
          "name": "黑色"
        },
        "10": {
          "code": 10,
          "name": "灰色"
        },
        "11": {
          "code": 11,
          "name": "粉色"
        },
        "12": {
          "code": 12,
          "name": "棕色"
        },
        "2": {
          "code": 2,
          "name": "白色"
        },
        "3": {
          "code": 3,
          "name": "红色"
        },
        "4": {
          "code": 4,
          "name": "橙色"
        },
        "5": {
          "code": 5,
          "name": "黄色"
        },
        "6": {
          "code": 6,
          "name": "绿色"
        },
        "7": {
          "code": 7,
          "name": "青色"
        },
        "8": {
          "code": 8,
          "name": "蓝色"
        },
        "9": {
          "code": 9,
          "name": "紫色"
        }
      },
      "code": "b",
      "code_order": 4,
      "codename": "颜色"
    },
    "missing_in": [
      "child_shoes_new_bar",
      "man_cotton_shoes_new_bar"
    ]
  },
  "{\"_child\": {\"11\": {\"code\": 13, \"name\": \"棉服\"}, \"12\": {\"code\": 8, \"name\": \"羽绒服\"}, \"125\": {\"code\": 125, \"name\": \"中裤\"}, \"167\": {\"code\": 167, \"name\": \"马甲\"}, \"20\": {\"code\": 36, \"name\": \"运动背心\"}, \"206\": {\"code\": 206, \"name\": \"凉拖鞋\"}, \"21\": {\"code\": 18, \"name\": \"编织衫\"}, \"333\": {\"code\": 333, \"name\": \"BRA\"}, \"34\": {\"code\": 6, \"name\": \"户外鞋\"}, \"347\": {\"code\": 347, \"name\": \"梭织厚外套\"}, \"39\": {\"code\": 5, \"name\": \"综训鞋\"}, \"40\": {\"code\": 4, \"name\": \"板鞋\"}, \"41\": {\"code\": 3, \"name\": \"休闲鞋\"}, \"42\": {\"code\": 1, \"name\": \"篮球鞋\"}, \"43\": {\"code\": 43, \"name\": \"短T\"}, \"45\": {\"code\": 45, \"name\": \"梭织薄外套\"}, \"47\": {\"code\": 47, \"name\": \"帽类\"}, \"48\": {\"code\": 48, \"name\": \"长T\"}, \"52\": {\"code\": 52, \"name\": \"袜类\"}, \"53\": {\"code\": 53, \"name\": \"短裤\"}, \"532\": {\"code\": 532, \"name\": \"针织类\"}, \"55\": {\"code\": 55, \"name\": \"两件套\"}, \"56\": {\"code\": 56, \"name\": \"套装\"}, \"59\": {\"code\": 59, \"name\": \"沙滩鞋\"}, \"6\": {\"code\": 29, \"name\": \"包类\"}, \"60\": {\"code\": 60, \"name\": \"背心\"}, \"62\": {\"code\": 62, \"name\": \"长裤\"}, \"63\": {\"code\": 63, \"name\": \"球类\"}, \"663\": {\"code\": 663, \"name\": \"裤装两件套\"}, \"67\": {\"code\": 67, \"name\": \"套头衫\"}, \"86\": {\"code\": 86, \"name\": \"针织运动上衣\"}, \"9\": {\"code\": 37, \"name\": \"七分裤\"}, \"99\": {\"code\": 99, \"name\": \"裙\"}}, \"code\": \"f\", \"code_order\": 28, \"codename\": \"品类\"}": {
    "element": {
      "_child": {
        "11": {
          "code": 13,
          "name": "棉服"
        },
        "12": {
          "code": 8,
          "name": "羽绒服"
        },
        "125": {
          "code": 125,
          "name": "中裤"
        },
        "167": {
          "code": 167,
          "name": "马甲"
        },
        "20": {
          "code": 36,
          "name": "运动背心"
        },
        "206": {
          "code": 206,
          "name": "凉拖鞋"
        },
        "21": {
          "code": 18,
          "name": "编织衫"
        },
        "333": {
          "code": 333,
          "name": "BRA"
        },
        "34": {
          "code": 6,
          "name": "户外鞋"
        },
        "347": {
          "code": 347,
          "name": "梭织厚外套"
        },
        "39": {
          "code": 5,
          "name": "综训鞋"
        },
        "40": {
          "code": 4,
          "name": "板鞋"
        },
        "41": {
          "code": 3,
          "name": "休闲鞋"
        },
        "42": {
          "code": 1,
          "name": "篮球鞋"
        },
        "43": {
          "code": 43,
          "name": "短T"
        },
        "45": {
          "code": 45,
          "name": "梭织薄外套"
        },
        "47": {
          "code": 47,
          "name": "帽类"
        },
        "48": {
          "code": 48,
          "name": "长T"
        },
        "52": {
          "code": 52,
          "name": "袜类"
        },
        "53": {
          "code": 53,
          "name": "短裤"
        },
        "532": {
          "code": 532,
          "name": "针织类"
        },
        "55": {
          "code": 55,
          "name": "两件套"
        },
        "56": {
          "code": 56,
          "name": "套装"
        },
        "59": {
          "code": 59,
          "name": "沙滩鞋"
        },
        "6": {
          "code": 29,
          "name": "包类"
        },
        "60": {
          "code": 60,
          "name": "背心"
        },
        "62": {
          "code": 62,
          "name": "长裤"
        },
        "63": {
          "code": 63,
          "name": "球类"
        },
        "663": {
          "code": 663,
          "name": "裤装两件套"
        },
        "67": {
          "code": 67,
          "name": "套头衫"
        },
        "86": {
          "code": 86,
          "name": "针织运动上衣"
        },
        "9": {
          "code": 37,
          "name": "七分裤"
        },
        "99": {
          "code": 99,
          "name": "裙"
        }
      },
      "code": "f",
      "code_order": 28,
      "codename": "品类"
    },
    "missing_in": [
      "child_shoes_new_bar",
      "man_new_bar",
      "man_shoes_new_bar",
      "man_cotton_shoes_new_bar"
    ]
  },
  "{\"_child\": {\"39\": {\"code\": 5, \"name\": \"综训鞋\"}, \"40\": {\"code\": 4, \"name\": \"板鞋\"}, \"41\": {\"code\": 3, \"name\": \"休闲鞋\"}, \"42\": {\"code\": 1, \"name\": \"篮球鞋\"}, \"43\": {\"code\": 2, \"name\": \"跑鞋\"}, \"59\": {\"code\": 59, \"name\": \"沙滩鞋\"}, \"9\": {\"code\": 26, \"name\": \"棉鞋\"}}, \"code\": \"f\", \"code_order\": 28, \"codename\": \"品类\"}": {
    "element": {
      "_child": {
        "39": {
          "code": 5,
          "name": "综训鞋"
        },
        "40": {
          "code": 4,
          "name": "板鞋"
        },
        "41": {
          "code": 3,
          "name": "休闲鞋"
        },
        "42": {
          "code": 1,
          "name": "篮球鞋"
        },
        "43": {
          "code": 2,
          "name": "跑鞋"
        },
        "59": {
          "code": 59,
          "name": "沙滩鞋"
        },
        "9": {
          "code": 26,
          "name": "棉鞋"
        }
      },
      "code": "f",
      "code_order": 28,
      "codename": "品类"
    },
    "missing_in": [
      "all_new_bar",
      "man_new_bar",
      "man_shoes_new_bar",
      "man_cotton_shoes_new_bar"
    ]
  },
  "{\"_child\": {\"100\": {\"code\": 46, \"name\": \"165\"}, \"101\": {\"code\": 28, \"name\": \"170\"}, \"102\": {\"code\": 80, \"name\": \"175\"}, \"25\": {\"code\": 72, \"name\": \"22\"}, \"26\": {\"code\": 73, \"name\": \"23\"}, \"27\": {\"code\": 74, \"name\": \"24\"}, \"28\": {\"code\": 75, \"name\": \"25\"}, \"29\": {\"code\": 43, \"name\": \"26\"}, \"30\": {\"code\": 44, \"name\": \"27\"}, \"31\": {\"code\": 40, \"name\": \"28\"}, \"32\": {\"code\": 41, \"name\": \"29\"}, \"33\": {\"code\": 42, \"name\": \"30\"}, \"34\": {\"code\": 22, \"name\": \"31\"}, \"35\": {\"code\": 23, \"name\": \"32\"}, \"36\": {\"code\": 20, \"name\": \"33\"}, \"37\": {\"code\": 21, \"name\": \"34\"}, \"38\": {\"code\": 13, \"name\": \"35\"}, \"40\": {\"code\": 14, \"name\": \"36\"}, \"42\": {\"code\": 15, \"name\": \"37\"}, \"43\": {\"code\": 49, \"name\": \"37.5\"}, \"44\": {\"code\": 16, \"name\": \"38\"}, \"46\": {\"code\": 7, \"name\": \"39\"}, \"47\": {\"code\": 8, \"name\": \"40\"}, \"48\": {\"code\": 52, \"name\": \"40.5\"}, \"49\": {\"code\": 9, \"name\": \"41\"}, \"503\": {\"code\": 29, \"name\": \"XS\"}, \"51\": {\"code\": 10, \"name\": \"42\"}, \"515\": {\"code\": 5, \"name\": \"S\"}, \"52\": {\"code\": 53, \"name\": \"42.5\"}, \"53\": {\"code\": 11, \"name\": \"43\"}, \"541\": {\"code\": 4, \"name\": \"M\"}, \"55\": {\"code\": 12, \"name\": \"44\"}, \"56\": {\"code\": 51, \"name\": \"44.5\"}, \"563\": {\"code\": 3, \"name\": \"L\"}, \"57\": {\"code\": 17, \"name\": \"45\"}, \"586\": {\"code\": 6, \"name\": \"XL\"}, \"59\": {\"code\": 18, \"name\": \"46\"}, \"61\": {\"code\": 45, \"name\": \"47\"}, \"62\": {\"code\": 67, \"name\": \"48\"}, \"621\": {\"code\": 1, \"name\": \"2XL\"}, \"637\": {\"code\": 2, \"name\": \"3XL\"}, \"646\": {\"code\": 19, \"name\": \"4XL\"}, \"653\": {\"code\": 66, \"name\": \"5XL\"}, \"87\": {\"code\": 30, \"name\": \"101\"}, \"892\": {\"code\": 110, \"name\": \"均码\"}, \"91\": {\"code\": 31, \"name\": \"110\"}, \"93\": {\"code\": 32, \"name\": \"120\"}, \"94\": {\"code\": 24, \"name\": \"130\"}, \"96\": {\"code\": 25, \"name\": \"140\"}, \"97\": {\"code\": 26, \"name\": \"150\"}, \"99\": {\"code\": 27, \"name\": \"160\"}}, \"code\": \"c\", \"code_order\": 27, \"codename\": \"尺码\"}": {
    "element": {
      "_child": {
        "100": {
          "code": 46,
          "name": "165"
        },
        "101": {
          "code": 28,
          "name": "170"
        },
        "102": {
          "code": 80,
          "name": "175"
        },
        "25": {
          "code": 72,
          "name": "22"
        },
        "26": {
          "code": 73,
          "name": "23"
        },
        "27": {
          "code": 74,
          "name": "24"
        },
        "28": {
          "code": 75,
          "name": "25"
        },
        "29": {
          "code": 43,
          "name": "26"
        },
        "30": {
          "code": 44,
          "name": "27"
        },
        "31": {
          "code": 40,
          "name": "28"
        },
        "32": {
          "code": 41,
          "name": "29"
        },
        "33": {
          "code": 42,
          "name": "30"
        },
        "34": {
          "code": 22,
          "name": "31"
        },
        "35": {
          "code": 23,
          "name": "32"
        },
        "36": {
          "code": 20,
          "name": "33"
        },
        "37": {
          "code": 21,
          "name": "34"
        },
        "38": {
          "code": 13,
          "name": "35"
        },
        "40": {
          "code": 14,
          "name": "36"
        },
        "42": {
          "code": 15,
          "name": "37"
        },
        "43": {
          "code": 49,
          "name": "37.5"
        },
        "44": {
          "code": 16,
          "name": "38"
        },
        "46": {
          "code": 7,
          "name": "39"
        },
        "47": {
          "code": 8,
          "name": "40"
        },
        "48": {
          "code": 52,
          "name": "40.5"
        },
        "49": {
          "code": 9,
          "name": "41"
        },
        "503": {
          "code": 29,
          "name": "XS"
        },
        "51": {
          "code": 10,
          "name": "42"
        },
        "515": {
          "code": 5,
          "name": "S"
        },
        "52": {
          "code": 53,
          "name": "42.5"
        },
        "53": {
          "code": 11,
          "name": "43"
        },
        "541": {
          "code": 4,
          "name": "M"
        },
        "55": {
          "code": 12,
          "name": "44"
        },
        "56": {
          "code": 51,
          "name": "44.5"
        },
        "563": {
          "code": 3,
          "name": "L"
        },
        "57": {
          "code": 17,
          "name": "45"
        },
        "586": {
          "code": 6,
          "name": "XL"
        },
        "59": {
          "code": 18,
          "name": "46"
        },
        "61": {
          "code": 45,
          "name": "47"
        },
        "62": {
          "code": 67,
          "name": "48"
        },
        "621": {
          "code": 1,
          "name": "2XL"
        },
        "637": {
          "code": 2,
          "name": "3XL"
        },
        "646": {
          "code": 19,
          "name": "4XL"
        },
        "653": {
          "code": 66,
          "name": "5XL"
        },
        "87": {
          "code": 30,
          "name": "101"
        },
        "892": {
          "code": 110,
          "name": "均码"
        },
        "91": {
          "code": 31,
          "name": "110"
        },
        "93": {
          "code": 32,
          "name": "120"
        },
        "94": {
          "code": 24,
          "name": "130"
        },
        "96": {
          "code": 25,
          "name": "140"
        },
        "97": {
          "code": 26,
          "name": "150"
        },
        "99": {
          "code": 27,
          "name": "160"
        }
      },
      "code": "c",
      "code_order": 27,
      "codename": "尺码"
    },
    "missing_in": [
      "child_shoes_new_bar",
      "all_new_bar",
      "man_shoes_new_bar",
      "man_cotton_shoes_new_bar"
    ]
  },
  "{\"_child\": {\"1\": {\"code\": 1, \"name\": \"鞋类\"}, \"2\": {\"code\": 2, \"name\": \"服装\"}, \"3\": {\"code\": 3, \"name\": \"配件\"}}, \"code\": \"e\", \"code_order\": 29, \"codename\": \"大类\"}": {
    "element": {
      "_child": {
        "1": {
          "code": 1,
          "name": "鞋类"
        },
        "2": {
          "code": 2,
          "name": "服装"
        },
        "3": {
          "code": 3,
          "name": "配件"
        }
      },
      "code": "e",
      "code_order": 29,
      "codename": "大类"
    },
    "missing_in": [
      "child_shoes_new_bar",
      "man_shoes_new_bar",
      "man_cotton_shoes_new_bar"
    ]
  },
  "{\"_child\": {\"100\": {\"code\": 46, \"name\": \"165\"}, \"101\": {\"code\": 28, \"name\": \"170\"}, \"102\": {\"code\": 80, \"name\": \"175\"}, \"11\": {\"code\": 56, \"name\": \"7\"}, \"25\": {\"code\": 72, \"name\": \"22\"}, \"26\": {\"code\": 73, \"name\": \"23\"}, \"27\": {\"code\": 74, \"name\": \"24\"}, \"28\": {\"code\": 75, \"name\": \"25\"}, \"29\": {\"code\": 43, \"name\": \"26\"}, \"30\": {\"code\": 44, \"name\": \"27\"}, \"31\": {\"code\": 40, \"name\": \"28\"}, \"32\": {\"code\": 41, \"name\": \"29\"}, \"33\": {\"code\": 42, \"name\": \"30\"}, \"34\": {\"code\": 22, \"name\": \"31\"}, \"35\": {\"code\": 23, \"name\": \"32\"}, \"36\": {\"code\": 20, \"name\": \"33\"}, \"37\": {\"code\": 21, \"name\": \"34\"}, \"38\": {\"code\": 13, \"name\": \"35\"}, \"39\": {\"code\": 47, \"name\": \"35.5\"}, \"40\": {\"code\": 14, \"name\": \"36\"}, \"41\": {\"code\": 48, \"name\": \"36.5\"}, \"42\": {\"code\": 15, \"name\": \"37\"}, \"43\": {\"code\": 49, \"name\": \"37.5\"}, \"44\": {\"code\": 16, \"name\": \"38\"}, \"45\": {\"code\": 50, \"name\": \"38.5\"}, \"46\": {\"code\": 7, \"name\": \"39\"}, \"47\": {\"code\": 8, \"name\": \"40\"}, \"48\": {\"code\": 52, \"name\": \"40.5\"}, \"49\": {\"code\": 9, \"name\": \"41\"}, \"503\": {\"code\": 29, \"name\": \"XS\"}, \"51\": {\"code\": 10, \"name\": \"42\"}, \"515\": {\"code\": 5, \"name\": \"S\"}, \"52\": {\"code\": 53, \"name\": \"42.5\"}, \"53\": {\"code\": 11, \"name\": \"43\"}, \"541\": {\"code\": 4, \"name\": \"M\"}, \"55\": {\"code\": 12, \"name\": \"44\"}, \"56\": {\"code\": 51, \"name\": \"44.5\"}, \"563\": {\"code\": 3, \"name\": \"L\"}, \"57\": {\"code\": 17, \"name\": \"45\"}, \"586\": {\"code\": 6, \"name\": \"XL\"}, \"59\": {\"code\": 18, \"name\": \"46\"}, \"61\": {\"code\": 45, \"name\": \"47\"}, \"62\": {\"code\": 67, \"name\": \"48\"}, \"621\": {\"code\": 1, \"name\": \"2XL\"}, \"637\": {\"code\": 2, \"name\": \"3XL\"}, \"646\": {\"code\": 19, \"name\": \"4XL\"}, \"653\": {\"code\": 66, \"name\": \"5XL\"}, \"7\": {\"code\": 62, \"name\": \"5\"}, \"87\": {\"code\": 30, \"name\": \"101\"}, \"892\": {\"code\": 110, \"name\": \"均码\"}, \"91\": {\"code\": 31, \"name\": \"110\"}, \"93\": {\"code\": 32, \"name\": \"120\"}, \"94\": {\"code\": 24, \"name\": \"130\"}, \"96\": {\"code\": 25, \"name\": \"140\"}, \"97\": {\"code\": 26, \"name\": \"150\"}, \"99\": {\"code\": 27, \"name\": \"160\"}}, \"code\": \"c\", \"code_order\": 27, \"codename\": \"尺码\"}": {
    "element": {
      "_child": {
        "100": {
          "code": 46,
          "name": "165"
        },
        "101": {
          "code": 28,
          "name": "170"
        },
        "102": {
          "code": 80,
          "name": "175"
        },
        "11": {
          "code": 56,
          "name": "7"
        },
        "25": {
          "code": 72,
          "name": "22"
        },
        "26": {
          "code": 73,
          "name": "23"
        },
        "27": {
          "code": 74,
          "name": "24"
        },
        "28": {
          "code": 75,
          "name": "25"
        },
        "29": {
          "code": 43,
          "name": "26"
        },
        "30": {
          "code": 44,
          "name": "27"
        },
        "31": {
          "code": 40,
          "name": "28"
        },
        "32": {
          "code": 41,
          "name": "29"
        },
        "33": {
          "code": 42,
          "name": "30"
        },
        "34": {
          "code": 22,
          "name": "31"
        },
        "35": {
          "code": 23,
          "name": "32"
        },
        "36": {
          "code": 20,
          "name": "33"
        },
        "37": {
          "code": 21,
          "name": "34"
        },
        "38": {
          "code": 13,
          "name": "35"
        },
        "39": {
          "code": 47,
          "name": "35.5"
        },
        "40": {
          "code": 14,
          "name": "36"
        },
        "41": {
          "code": 48,
          "name": "36.5"
        },
        "42": {
          "code": 15,
          "name": "37"
        },
        "43": {
          "code": 49,
          "name": "37.5"
        },
        "44": {
          "code": 16,
          "name": "38"
        },
        "45": {
          "code": 50,
          "name": "38.5"
        },
        "46": {
          "code": 7,
          "name": "39"
        },
        "47": {
          "code": 8,
          "name": "40"
        },
        "48": {
          "code": 52,
          "name": "40.5"
        },
        "49": {
          "code": 9,
          "name": "41"
        },
        "503": {
          "code": 29,
          "name": "XS"
        },
        "51": {
          "code": 10,
          "name": "42"
        },
        "515": {
          "code": 5,
          "name": "S"
        },
        "52": {
          "code": 53,
          "name": "42.5"
        },
        "53": {
          "code": 11,
          "name": "43"
        },
        "541": {
          "code": 4,
          "name": "M"
        },
        "55": {
          "code": 12,
          "name": "44"
        },
        "56": {
          "code": 51,
          "name": "44.5"
        },
        "563": {
          "code": 3,
          "name": "L"
        },
        "57": {
          "code": 17,
          "name": "45"
        },
        "586": {
          "code": 6,
          "name": "XL"
        },
        "59": {
          "code": 18,
          "name": "46"
        },
        "61": {
          "code": 45,
          "name": "47"
        },
        "62": {
          "code": 67,
          "name": "48"
        },
        "621": {
          "code": 1,
          "name": "2XL"
        },
        "637": {
          "code": 2,
          "name": "3XL"
        },
        "646": {
          "code": 19,
          "name": "4XL"
        },
        "653": {
          "code": 66,
          "name": "5XL"
        },
        "7": {
          "code": 62,
          "name": "5"
        },
        "87": {
          "code": 30,
          "name": "101"
        },
        "892": {
          "code": 110,
          "name": "均码"
        },
        "91": {
          "code": 31,
          "name": "110"
        },
        "93": {
          "code": 32,
          "name": "120"
        },
        "94": {
          "code": 24,
          "name": "130"
        },
        "96": {
          "code": 25,
          "name": "140"
        },
        "97": {
          "code": 26,
          "name": "150"
        },
        "99": {
          "code": 27,
          "name": "160"
        }
      },
      "code": "c",
      "code_order": 27,
      "codename": "尺码"
    },
    "missing_in": [
      "child_shoes_new_bar",
      "man_new_bar",
      "man_shoes_new_bar",
      "man_cotton_shoes_new_bar"
    ]
  },
  "{\"_child\": {\"1\": {\"code\": 1, \"name\": \"黑色\"}, \"2\": {\"code\": 2, \"name\": \"白色\"}, \"3\": {\"code\": 3, \"name\": \"红色\"}, \"4\": {\"code\": 4, \"name\": \"橙色\"}, \"5\": {\"code\": 5, \"name\": \"黄色\"}}, \"code\": \"b\", \"code_order\": 4, \"codename\": \"颜色\"}": {
    "element": {
      "_child": {
        "1": {
          "code": 1,
          "name": "黑色"
        },
        "2": {
          "code": 2,
          "name": "白色"
        },
        "3": {
          "code": 3,
          "name": "红色"
        },
        "4": {
          "code": 4,
          "name": "橙色"
        },
        "5": {
          "code": 5,
          "name": "黄色"
        }
      },
      "code": "b",
      "code_order": 4,
      "codename": "颜色"
    },
    "missing_in": [
      "child_shoes_new_bar",
      "all_new_bar",
      "man_new_bar",
      "man_shoes_new_bar"
    ]
  },
  "{\"_child\": {\"13\": {\"code\": 13, \"name\": \"大童\"}, \"8\": {\"code\": 8, \"name\": \"小童\"}, \"9\": {\"code\": 9, \"name\": \"婴童\"}}, \"code\": \"y\", \"code_order\": 8, \"codename\": \"年龄段\"}": {
    "element": {
      "_child": {
        "13": {
          "code": 13,
          "name": "大童"
        },
        "8": {
          "code": 8,
          "name": "小童"
        },
        "9": {
          "code": 9,
          "name": "婴童"
        }
      },
      "code": "y",
      "code_order": 8,
      "codename": "年龄段"
    },
    "missing_in": [
      "man_cotton_shoes_new_bar"
    ]
  },
  "{\"_child\": {\"31\": {\"code\": 40, \"name\": \"28\"}, \"32\": {\"code\": 41, \"name\": \"29\"}, \"33\": {\"code\": 42, \"name\": \"30\"}, \"34\": {\"code\": 22, \"name\": \"31\"}, \"35\": {\"code\": 23, \"name\": \"32\"}, \"36\": {\"code\": 20, \"name\": \"33\"}, \"37\": {\"code\": 21, \"name\": \"34\"}, \"38\": {\"code\": 13, \"name\": \"35\"}, \"40\": {\"code\": 14, \"name\": \"36\"}, \"42\": {\"code\": 15, \"name\": \"37\"}, \"44\": {\"code\": 16, \"name\": \"38\"}, \"46\": {\"code\": 7, \"name\": \"39\"}, \"47\": {\"code\": 8, \"name\": \"40\"}, \"48\": {\"code\": 52, \"name\": \"40.5\"}, \"49\": {\"code\": 9, \"name\": \"41\"}, \"51\": {\"code\": 10, \"name\": \"42\"}, \"52\": {\"code\": 53, \"name\": \"42.5\"}, \"53\": {\"code\": 11, \"name\": \"43\"}, \"55\": {\"code\": 12, \"name\": \"44\"}}, \"code\": \"c\", \"code_order\": 27, \"codename\": \"尺码\"}": {
    "element": {
      "_child": {
        "31": {
          "code": 40,
          "name": "28"
        },
        "32": {
          "code": 41,
          "name": "29"
        },
        "33": {
          "code": 42,
          "name": "30"
        },
        "34": {
          "code": 22,
          "name": "31"
        },
        "35": {
          "code": 23,
          "name": "32"
        },
        "36": {
          "code": 20,
          "name": "33"
        },
        "37": {
          "code": 21,
          "name": "34"
        },
        "38": {
          "code": 13,
          "name": "35"
        },
        "40": {
          "code": 14,
          "name": "36"
        },
        "42": {
          "code": 15,
          "name": "37"
        },
        "44": {
          "code": 16,
          "name": "38"
        },
        "46": {
          "code": 7,
          "name": "39"
        },
        "47": {
          "code": 8,
          "name": "40"
        },
        "48": {
          "code": 52,
          "name": "40.5"
        },
        "49": {
          "code": 9,
          "name": "41"
        },
        "51": {
          "code": 10,
          "name": "42"
        },
        "52": {
          "code": 53,
          "name": "42.5"
        },
        "53": {
          "code": 11,
          "name": "43"
        },
        "55": {
          "code": 12,
          "name": "44"
        }
      },
      "code": "c",
      "code_order": 27,
      "codename": "尺码"
    },
    "missing_in": [
      "child_shoes_new_bar",
      "all_new_bar",
      "man_new_bar",
      "man_shoes_new_bar"
    ]
  },
  "{\"_child\": {\"1\": {\"code\": 1, \"name\": \"黑色\"}, \"2\": {\"code\": 2, \"name\": \"白色\"}, \"3\": {\"code\": 3, \"name\": \"红色\"}, \"4\": {\"code\": 4, \"name\": \"橙色\"}, \"5\": {\"code\": 5, \"name\": \"黄色\"}, \"6\": {\"code\": 6, \"name\": \"绿色\"}}, \"code\": \"b\", \"code_order\": 4, \"codename\": \"颜色\"}": {
    "element": {
      "_child": {
        "1": {
          "code": 1,
          "name": "黑色"
        },
        "2": {
          "code": 2,
          "name": "白色"
        },
        "3": {
          "code": 3,
          "name": "红色"
        },
        "4": {
          "code": 4,
          "name": "橙色"
        },
        "5": {
          "code": 5,
          "name": "黄色"
        },
        "6": {
          "code": 6,
          "name": "绿色"
        }
      },
      "code": "b",
      "code_order": 4,
      "codename": "颜色"
    },
    "missing_in": [
      "all_new_bar",
      "man_new_bar",
      "man_shoes_new_bar",
      "man_cotton_shoes_new_bar"
    ]
  },
  "{\"_child\": {\"10\": {\"code\": 14, \"name\": \"防泼水\"}}, \"code\": \"h\", \"code_order\": 21, \"codename\": \"科技\"}": {
    "element": {
      "_child": {
        "10": {
          "code": 14,
          "name": "防泼水"
        }
      },
      "code": "h",
      "code_order": 21,
      "codename": "科技"
    },
    "missing_in": [
      "child_shoes_new_bar",
      "all_new_bar",
      "man_shoes_new_bar",
      "man_cotton_shoes_new_bar"
    ]
  },
  "{\"_child\": {\"1\": {\"code\": 4, \"name\": \"网球系列\"}, \"3\": {\"code\": 7, \"name\": \"户外系列\"}, \"4\": {\"code\": 3, \"name\": \"足球系列\"}, \"5\": {\"code\": 8, \"name\": \"综训系列\"}, \"6\": {\"code\": 9, \"name\": \"生活系列\"}, \"7\": {\"code\": 2, \"name\": \"篮球系列\"}, \"8\": {\"code\": 6, \"name\": \"跑步系列\"}}, \"code\": \"g\", \"code_order\": 23, \"codename\": \"系列\"}": {
    "element": {
      "_child": {
        "1": {
          "code": 4,
          "name": "网球系列"
        },
        "3": {
          "code": 7,
          "name": "户外系列"
        },
        "4": {
          "code": 3,
          "name": "足球系列"
        },
        "5": {
          "code": 8,
          "name": "综训系列"
        },
        "6": {
          "code": 9,
          "name": "生活系列"
        },
        "7": {
          "code": 2,
          "name": "篮球系列"
        },
        "8": {
          "code": 6,
          "name": "跑步系列"
        }
      },
      "code": "g",
      "code_order": 23,
      "codename": "系列"
    },
    "missing_in": [
      "child_shoes_new_bar",
      "man_new_bar",
      "man_shoes_new_bar",
      "man_cotton_shoes_new_bar"
    ]
  },
  "{\"_child\": {\"25\": {\"code\": 72, \"name\": \"22\"}, \"26\": {\"code\": 73, \"name\": \"23\"}, \"27\": {\"code\": 74, \"name\": \"24\"}, \"28\": {\"code\": 75, \"name\": \"25\"}, \"29\": {\"code\": 43, \"name\": \"26\"}, \"30\": {\"code\": 44, \"name\": \"27\"}, \"31\": {\"code\": 40, \"name\": \"28\"}, \"32\": {\"code\": 41, \"name\": \"29\"}, \"33\": {\"code\": 42, \"name\": \"30\"}, \"34\": {\"code\": 22, \"name\": \"31\"}, \"35\": {\"code\": 23, \"name\": \"32\"}, \"36\": {\"code\": 20, \"name\": \"33\"}, \"37\": {\"code\": 21, \"name\": \"34\"}, \"38\": {\"code\": 13, \"name\": \"35\"}, \"40\": {\"code\": 14, \"name\": \"36\"}, \"42\": {\"code\": 15, \"name\": \"37\"}, \"43\": {\"code\": 49, \"name\": \"37.5\"}, \"44\": {\"code\": 16, \"name\": \"38\"}, \"46\": {\"code\": 7, \"name\": \"39\"}, \"47\": {\"code\": 8, \"name\": \"40\"}, \"48\": {\"code\": 52, \"name\": \"40.5\"}, \"49\": {\"code\": 9, \"name\": \"41\"}, \"51\": {\"code\": 10, \"name\": \"42\"}, \"52\": {\"code\": 53, \"name\": \"42.5\"}, \"53\": {\"code\": 11, \"name\": \"43\"}, \"55\": {\"code\": 12, \"name\": \"44\"}, \"56\": {\"code\": 51, \"name\": \"44.5\"}, \"57\": {\"code\": 17, \"name\": \"45\"}, \"59\": {\"code\": 18, \"name\": \"46\"}, \"61\": {\"code\": 45, \"name\": \"47\"}, \"62\": {\"code\": 67, \"name\": \"48\"}}, \"code\": \"c\", \"code_order\": 27, \"codename\": \"尺码\"}": {
    "element": {
      "_child": {
        "25": {
          "code": 72,
          "name": "22"
        },
        "26": {
          "code": 73,
          "name": "23"
        },
        "27": {
          "code": 74,
          "name": "24"
        },
        "28": {
          "code": 75,
          "name": "25"
        },
        "29": {
          "code": 43,
          "name": "26"
        },
        "30": {
          "code": 44,
          "name": "27"
        },
        "31": {
          "code": 40,
          "name": "28"
        },
        "32": {
          "code": 41,
          "name": "29"
        },
        "33": {
          "code": 42,
          "name": "30"
        },
        "34": {
          "code": 22,
          "name": "31"
        },
        "35": {
          "code": 23,
          "name": "32"
        },
        "36": {
          "code": 20,
          "name": "33"
        },
        "37": {
          "code": 21,
          "name": "34"
        },
        "38": {
          "code": 13,
          "name": "35"
        },
        "40": {
          "code": 14,
          "name": "36"
        },
        "42": {
          "code": 15,
          "name": "37"
        },
        "43": {
          "code": 49,
          "name": "37.5"
        },
        "44": {
          "code": 16,
          "name": "38"
        },
        "46": {
          "code": 7,
          "name": "39"
        },
        "47": {
          "code": 8,
          "name": "40"
        },
        "48": {
          "code": 52,
          "name": "40.5"
        },
        "49": {
          "code": 9,
          "name": "41"
        },
        "51": {
          "code": 10,
          "name": "42"
        },
        "52": {
          "code": 53,
          "name": "42.5"
        },
        "53": {
          "code": 11,
          "name": "43"
        },
        "55": {
          "code": 12,
          "name": "44"
        },
        "56": {
          "code": 51,
          "name": "44.5"
        },
        "57": {
          "code": 17,
          "name": "45"
        },
        "59": {
          "code": 18,
          "name": "46"
        },
        "61": {
          "code": 45,
          "name": "47"
        },
        "62": {
          "code": 67,
          "name": "48"
        }
      },
      "code": "c",
      "code_order": 27,
      "codename": "尺码"
    },
    "missing_in": [
      "child_shoes_new_bar",
      "all_new_bar",
      "man_new_bar",
      "man_cotton_shoes_new_bar"
    ]
  }
}